chainstream/__init__.py
chainstream/py.typed
chainstream-1.0.2.dist-info/METADATA
chainstream-1.0.2.dist-info/WHEEL
chainstream-1.0.2.dist-info/top_level.txt
chainstream-1.0.2.dist-info/RECORD
