Metadata-Version: 2.1
Name: chainstream
Version: 1.0.2
Summary: Chain I/O streams together
Author-email: Reuben Thomas <rrt@c3d.org>
License: CC-BY-SA 4.0
Project-URL: Homepage, https://github.com/rrthomas/chainstream
Classifier: Programming Language :: Python :: 3
Requires-Python: >=3.9
